[{"game_date":"2023-07-15","winrate_each_day":0,"games_played":1,"games_won":0,"aggregate_winrate":0},{"game_date":"2023-07-16","winrate_each_day":0,"games_played":2,"games_won":0,"aggregate_winrate":0},{"game_date":"2023-07-18","winrate_each_day":0.5,"games_played":4,"games_won":2,"aggregate_winrate":0.2857142857142857},{"game_date":"2023-07-20","winrate_each_day":0,"games_played":1,"games_won":0,"aggregate_winrate":0.25},{"game_date":"2023-07-21","winrate_each_day":0.8333333333333334,"games_played":6,"games_won":5,"aggregate_winrate":0.5},{"game_date":"2023-07-25","winrate_each_day":1,"games_played":1,"games_won":1,"aggregate_winrate":0.5333333333333333},{"game_date":"2023-07-27","winrate_each_day":1,"games_played":1,"games_won":1,"aggregate_winrate":0.5625},{"game_date":"2023-07-29","winrate_each_day":1,"games_played":2,"games_won":2,"aggregate_winrate":0.6111111111111112},{"game_date":"2023-08-02","winrate_each_day":0,"games_played":1,"games_won":0,"aggregate_winrate":0.5789473684210527},{"game_date":"2023-08-06","winrate_each_day":1,"games_played":1,"games_won":1,"aggregate_winrate":0.6},{"game_date":"2023-08-08","winrate_each_day":0.5714285714285714,"games_played":7,"games_won":4,"aggregate_winrate":0.5925925925925926},{"game_date":"2023-08-09","winrate_each_day":0,"games_played":1,"games_won":0,"aggregate_winrate":0.5714285714285714},{"game_date":"2023-08-14","winrate_each_day":0.6666666666666666,"games_played":3,"games_won":2,"aggregate_winrate":0.5806451612903226},{"game_date":"2023-08-15","winrate_each_day":0,"games_played":1,"games_won":0,"aggregate_winrate":0.5625},{"game_date":"2023-08-18","winrate_each_day":0.5,"games_played":6,"games_won":3,"aggregate_winrate":0.5526315789473685},{"game_date":"2023-08-20","winrate_each_day":0.6666666666666666,"games_played":3,"games_won":2,"aggregate_winrate":0.5609756097560976},{"game_date":"2023-08-21","winrate_each_day":0.5,"games_played":4,"games_won":2,"aggregate_winrate":0.5555555555555556},{"game_date":"2023-08-23","winrate_each_day":1,"games_played":2,"games_won":2,"aggregate_winrate":0.574468085106383},{"game_date":"2023-08-25","winrate_each_day":1,"games_played":2,"games_won":2,"aggregate_winrate":0.5918367346938775},{"game_date":"2023-08-26","winrate_each_day":0.3333333333333333,"games_played":6,"games_won":2,"aggregate_winrate":0.5636363636363636},{"game_date":"2023-08-28","winrate_each_day":0.25,"games_played":4,"games_won":1,"aggregate_winrate":0.5423728813559322},{"game_date":"2023-08-30","winrate_each_day":0.5,"games_played":4,"games_won":2,"aggregate_winrate":0.5396825396825397},{"game_date":"2023-09-01","winrate_each_day":0.6,"games_played":5,"games_won":3,"aggregate_winrate":0.5441176470588235},{"game_date":"2023-09-02","winrate_each_day":0.42857142857142855,"games_played":7,"games_won":3,"aggregate_winrate":0.5333333333333333},{"game_date":"2023-09-03","winrate_each_day":0.42857142857142855,"games_played":7,"games_won":3,"aggregate_winrate":0.524390243902439},{"game_date":"2023-09-06","winrate_each_day":0,"games_played":3,"games_won":0,"aggregate_winrate":0.5058823529411764},{"game_date":"2023-09-08","winrate_each_day":0.3333333333333333,"games_played":6,"games_won":2,"aggregate_winrate":0.4945054945054945},{"game_date":"2023-09-09","winrate_each_day":0.6,"games_played":5,"games_won":3,"aggregate_winrate":0.5},{"game_date":"2023-09-10","winrate_each_day":0,"games_played":1,"games_won":0,"aggregate_winrate":0.4948453608247423},{"game_date":"2023-09-11","winrate_each_day":0.5,"games_played":2,"games_won":1,"aggregate_winrate":0.494949494949495},{"game_date":"2023-09-13","winrate_each_day":0.5,"games_played":4,"games_won":2,"aggregate_winrate":0.49514563106796117},{"game_date":"2023-09-15","winrate_each_day":0.3333333333333333,"games_played":9,"games_won":3,"aggregate_winrate":0.48214285714285715},{"game_date":"2023-09-18","winrate_each_day":0,"games_played":6,"games_won":0,"aggregate_winrate":0.4576271186440678},{"game_date":"2023-09-19","winrate_each_day":0,"games_played":1,"games_won":0,"aggregate_winrate":0.453781512605042},{"game_date":"2023-09-22","winrate_each_day":0.2,"games_played":10,"games_won":2,"aggregate_winrate":0.43410852713178294},{"game_date":"2023-09-24","winrate_each_day":0.4,"games_played":5,"games_won":2,"aggregate_winrate":0.43283582089552236},{"game_date":"2023-09-25","winrate_each_day":1,"games_played":1,"games_won":1,"aggregate_winrate":0.43703703703703706},{"game_date":"2023-09-26","winrate_each_day":0.6666666666666666,"games_played":9,"games_won":6,"aggregate_winrate":0.4513888888888889},{"game_date":"2023-09-27","winrate_each_day":0,"games_played":4,"games_won":0,"aggregate_winrate":0.4391891891891892},{"game_date":"2023-09-29","winrate_each_day":0.3333333333333333,"games_played":3,"games_won":1,"aggregate_winrate":0.4370860927152318},{"game_date":"2023-10-01","winrate_each_day":1,"games_played":1,"games_won":1,"aggregate_winrate":0.4407894736842105},{"game_date":"2023-10-12","winrate_each_day":0.25,"games_played":4,"games_won":1,"aggregate_winrate":0.4358974358974359},{"game_date":"2023-10-13","winrate_each_day":1,"games_played":2,"games_won":2,"aggregate_winrate":0.4430379746835443},{"game_date":"2023-10-14","winrate_each_day":0.8571428571428571,"games_played":7,"games_won":6,"aggregate_winrate":0.46060606060606063},{"game_date":"2023-10-15","winrate_each_day":0.5,"games_played":2,"games_won":1,"aggregate_winrate":0.46107784431137727},{"game_date":"2023-10-18","winrate_each_day":0.5,"games_played":4,"games_won":2,"aggregate_winrate":0.4619883040935672},{"game_date":"2023-10-19","winrate_each_day":0.6,"games_played":5,"games_won":3,"aggregate_winrate":0.4659090909090909},{"game_date":"2023-10-20","winrate_each_day":0.8,"games_played":5,"games_won":4,"aggregate_winrate":0.47513812154696133},{"game_date":"2023-10-22","winrate_each_day":0.4,"games_played":5,"games_won":2,"aggregate_winrate":0.4731182795698925},{"game_date":"2023-10-23","winrate_each_day":0.375,"games_played":8,"games_won":3,"aggregate_winrate":0.4690721649484536},{"game_date":"2023-10-24","winrate_each_day":0.6666666666666666,"games_played":3,"games_won":2,"aggregate_winrate":0.4720812182741117},{"game_date":"2023-10-26","winrate_each_day":0.3333333333333333,"games_played":3,"games_won":1,"aggregate_winrate":0.47},{"game_date":"2023-10-27","winrate_each_day":0.5714285714285714,"games_played":7,"games_won":4,"aggregate_winrate":0.47342995169082125},{"game_date":"2023-10-29","winrate_each_day":0,"games_played":2,"games_won":0,"aggregate_winrate":0.4688995215311005},{"game_date":"2023-10-31","winrate_each_day":0.75,"games_played":4,"games_won":3,"aggregate_winrate":0.47417840375586856},{"game_date":"2023-11-01","winrate_each_day":0.25,"games_played":4,"games_won":1,"aggregate_winrate":0.4700460829493088},{"game_date":"2023-11-02","winrate_each_day":0.7777777777777778,"games_played":9,"games_won":7,"aggregate_winrate":0.4823008849557522},{"game_date":"2023-11-03","winrate_each_day":0.5714285714285714,"games_played":7,"games_won":4,"aggregate_winrate":0.48497854077253216},{"game_date":"2023-11-05","winrate_each_day":0.6666666666666666,"games_played":6,"games_won":4,"aggregate_winrate":0.4895397489539749},{"game_date":"2023-11-06","winrate_each_day":0.6,"games_played":10,"games_won":6,"aggregate_winrate":0.4939759036144578},{"game_date":"2023-11-07","winrate_each_day":0,"games_played":3,"games_won":0,"aggregate_winrate":0.4880952380952381},{"game_date":"2023-11-10","winrate_each_day":0.6666666666666666,"games_played":6,"games_won":4,"aggregate_winrate":0.49224806201550386},{"game_date":"2023-11-11","winrate_each_day":0,"games_played":1,"games_won":0,"aggregate_winrate":0.49034749034749037},{"game_date":"2023-11-12","winrate_each_day":0.4,"games_played":5,"games_won":2,"aggregate_winrate":0.48863636363636365},{"game_date":"2023-11-13","winrate_each_day":0.6666666666666666,"games_played":3,"games_won":2,"aggregate_winrate":0.49063670411985016},{"game_date":"2023-11-15","winrate_each_day":0.75,"games_played":8,"games_won":6,"aggregate_winrate":0.49818181818181817},{"game_date":"2023-11-18","winrate_each_day":0.6,"games_played":5,"games_won":3,"aggregate_winrate":0.5},{"game_date":"2023-11-21","winrate_each_day":0.6666666666666666,"games_played":6,"games_won":4,"aggregate_winrate":0.5034965034965035},{"game_date":"2023-11-22","winrate_each_day":0.5,"games_played":4,"games_won":2,"aggregate_winrate":0.503448275862069},{"game_date":"2023-11-23","winrate_each_day":0.5,"games_played":10,"games_won":5,"aggregate_winrate":0.5033333333333333},{"game_date":"2023-11-29","winrate_each_day":0.6,"games_played":5,"games_won":3,"aggregate_winrate":0.5049180327868853},{"game_date":"2023-12-01","winrate_each_day":0.16666666666666666,"games_played":6,"games_won":1,"aggregate_winrate":0.4983922829581994},{"game_date":"2023-12-02","winrate_each_day":1,"games_played":2,"games_won":2,"aggregate_winrate":0.5015974440894568},{"game_date":"2023-12-03","winrate_each_day":0.75,"games_played":4,"games_won":3,"aggregate_winrate":0.5047318611987381},{"game_date":"2023-12-04","winrate_each_day":0.16666666666666666,"games_played":6,"games_won":1,"aggregate_winrate":0.4984520123839009},{"game_date":"2023-12-05","winrate_each_day":1,"games_played":1,"games_won":1,"aggregate_winrate":0.5},{"game_date":"2023-12-06","winrate_each_day":0.5,"games_played":2,"games_won":1,"aggregate_winrate":0.5},{"game_date":"2023-12-11","winrate_each_day":0.6666666666666666,"games_played":3,"games_won":2,"aggregate_winrate":0.5015197568389058},{"game_date":"2023-12-12","winrate_each_day":0.2,"games_played":5,"games_won":1,"aggregate_winrate":0.49700598802395207},{"game_date":"2023-12-13","winrate_each_day":0.8,"games_played":5,"games_won":4,"aggregate_winrate":0.5014749262536873},{"game_date":"2023-12-15","winrate_each_day":0.25,"games_played":4,"games_won":1,"aggregate_winrate":0.49854227405247814},{"game_date":"2023-12-18","winrate_each_day":0.3333333333333333,"games_played":6,"games_won":2,"aggregate_winrate":0.49570200573065903},{"game_date":"2023-12-20","winrate_each_day":0,"games_played":3,"games_won":0,"aggregate_winrate":0.4914772727272727},{"game_date":"2023-12-22","winrate_each_day":0.5,"games_played":4,"games_won":2,"aggregate_winrate":0.49157303370786515},{"game_date":"2023-12-23","winrate_each_day":0.75,"games_played":4,"games_won":3,"aggregate_winrate":0.49444444444444446},{"game_date":"2023-12-26","winrate_each_day":0.5,"games_played":6,"games_won":3,"aggregate_winrate":0.49453551912568305},{"game_date":"2023-12-27","winrate_each_day":1,"games_played":4,"games_won":4,"aggregate_winrate":0.5},{"game_date":"2023-12-28","winrate_each_day":0.6666666666666666,"games_played":9,"games_won":6,"aggregate_winrate":0.503957783641161},{"game_date":"2023-12-29","winrate_each_day":0.5,"games_played":4,"games_won":2,"aggregate_winrate":0.5039164490861618},{"game_date":"2024-01-02","winrate_each_day":0.2,"games_played":5,"games_won":1,"aggregate_winrate":0.5},{"game_date":"2024-01-03","winrate_each_day":0.5,"games_played":8,"games_won":4,"aggregate_winrate":0.5},{"game_date":"2024-01-04","winrate_each_day":0.5,"games_played":4,"games_won":2,"aggregate_winrate":0.5},{"game_date":"2024-01-05","winrate_each_day":0.5454545454545454,"games_played":11,"games_won":6,"aggregate_winrate":0.5012165450121655},{"game_date":"2024-01-06","winrate_each_day":0.4444444444444444,"games_played":9,"games_won":4,"aggregate_winrate":0.5},{"game_date":"2024-01-07","winrate_each_day":0.6666666666666666,"games_played":3,"games_won":2,"aggregate_winrate":0.5011820330969267},{"game_date":"2024-01-08","winrate_each_day":0.5,"games_played":4,"games_won":2,"aggregate_winrate":0.5011709601873536},{"game_date":"2024-01-09","winrate_each_day":0.5714285714285714,"games_played":7,"games_won":4,"aggregate_winrate":0.5023041474654378},{"game_date":"2024-01-11","winrate_each_day":0.7777777777777778,"games_played":9,"games_won":7,"aggregate_winrate":0.5079006772009029},{"game_date":"2024-01-12","winrate_each_day":0,"games_played":1,"games_won":0,"aggregate_winrate":0.5067567567567568},{"game_date":"2024-01-14","winrate_each_day":0.5,"games_played":6,"games_won":3,"aggregate_winrate":0.5066666666666667},{"game_date":"2024-01-16","winrate_each_day":0.25,"games_played":4,"games_won":1,"aggregate_winrate":0.5044052863436124},{"game_date":"2024-01-19","winrate_each_day":0.5714285714285714,"games_played":7,"games_won":4,"aggregate_winrate":0.5054229934924078},{"game_date":"2024-01-20","winrate_each_day":0.8,"games_played":5,"games_won":4,"aggregate_winrate":0.5085836909871244},{"game_date":"2024-01-21","winrate_each_day":0.2857142857142857,"games_played":7,"games_won":2,"aggregate_winrate":0.5052854122621564},{"game_date":"2024-01-22","winrate_each_day":0.5714285714285714,"games_played":7,"games_won":4,"aggregate_winrate":0.50625},{"game_date":"2024-01-23","winrate_each_day":0.6666666666666666,"games_played":3,"games_won":2,"aggregate_winrate":0.5072463768115942},{"game_date":"2024-01-25","winrate_each_day":0,"games_played":2,"games_won":0,"aggregate_winrate":0.5051546391752577},{"game_date":"2024-01-29","winrate_each_day":0.5,"games_played":4,"games_won":2,"aggregate_winrate":0.5051124744376279},{"game_date":"2024-01-30","winrate_each_day":0.4,"games_played":5,"games_won":2,"aggregate_winrate":0.5040485829959515},{"game_date":"2024-01-31","winrate_each_day":0,"games_played":1,"games_won":0,"aggregate_winrate":0.503030303030303},{"game_date":"2024-02-01","winrate_each_day":0.6666666666666666,"games_played":3,"games_won":2,"aggregate_winrate":0.5040160642570282},{"game_date":"2024-02-02","winrate_each_day":0,"games_played":2,"games_won":0,"aggregate_winrate":0.502},{"game_date":"2024-02-03","winrate_each_day":0.25,"games_played":4,"games_won":1,"aggregate_winrate":0.5},{"game_date":"2024-02-08","winrate_each_day":0.75,"games_played":8,"games_won":6,"aggregate_winrate":0.50390625},{"game_date":"2024-02-09","winrate_each_day":0,"games_played":1,"games_won":0,"aggregate_winrate":0.5029239766081871},{"game_date":"2024-02-11","winrate_each_day":0.8,"games_played":5,"games_won":4,"aggregate_winrate":0.5057915057915058},{"game_date":"2024-02-12","winrate_each_day":0,"games_played":1,"games_won":0,"aggregate_winrate":0.5048169556840078},{"game_date":"2024-02-14","winrate_each_day":0,"games_played":2,"games_won":0,"aggregate_winrate":0.5028790786948176},{"game_date":"2024-02-15","winrate_each_day":0,"games_played":1,"games_won":0,"aggregate_winrate":0.5019157088122606},{"game_date":"2024-02-16","winrate_each_day":1,"games_played":1,"games_won":1,"aggregate_winrate":0.502868068833652},{"game_date":"2024-02-17","winrate_each_day":0.2,"games_played":5,"games_won":1,"aggregate_winrate":0.5},{"game_date":"2024-02-18","winrate_each_day":0.3333333333333333,"games_played":6,"games_won":2,"aggregate_winrate":0.49812734082397003},{"game_date":"2024-02-19","winrate_each_day":0.5,"games_played":4,"games_won":2,"aggregate_winrate":0.49814126394052044},{"game_date":"2024-02-20","winrate_each_day":0.2,"games_played":5,"games_won":1,"aggregate_winrate":0.4953959484346225},{"game_date":"2024-02-21","winrate_each_day":0.9,"games_played":10,"games_won":9,"aggregate_winrate":0.5027124773960217},{"game_date":"2024-02-22","winrate_each_day":1,"games_played":2,"games_won":2,"aggregate_winrate":0.5045045045045045},{"game_date":"2024-02-23","winrate_each_day":0.5,"games_played":2,"games_won":1,"aggregate_winrate":0.5044883303411131},{"game_date":"2024-02-24","winrate_each_day":0,"games_played":1,"games_won":0,"aggregate_winrate":0.503584229390681},{"game_date":"2024-02-26","winrate_each_day":0.3333333333333333,"games_played":9,"games_won":3,"aggregate_winrate":0.5008818342151675},{"game_date":"2024-02-27","winrate_each_day":0.8,"games_played":5,"games_won":4,"aggregate_winrate":0.5034965034965035},{"game_date":"2024-02-29","winrate_each_day":0,"games_played":1,"games_won":0,"aggregate_winrate":0.5026178010471204},{"game_date":"2024-03-01","winrate_each_day":0.4,"games_played":5,"games_won":2,"aggregate_winrate":0.5017301038062284},{"game_date":"2024-03-02","winrate_each_day":0.5,"games_played":2,"games_won":1,"aggregate_winrate":0.5017241379310344},{"game_date":"2024-03-03","winrate_each_day":0.5,"games_played":6,"games_won":3,"aggregate_winrate":0.5017064846416383},{"game_date":"2024-03-05","winrate_each_day":0.7,"games_played":10,"games_won":7,"aggregate_winrate":0.5050335570469798},{"game_date":"2024-03-06","winrate_each_day":0.16666666666666666,"games_played":6,"games_won":1,"aggregate_winrate":0.5016611295681063},{"game_date":"2024-03-07","winrate_each_day":0.6,"games_played":5,"games_won":3,"aggregate_winrate":0.5024711696869851},{"game_date":"2024-03-08","winrate_each_day":0.5,"games_played":2,"games_won":1,"aggregate_winrate":0.5024630541871922},{"game_date":"2024-03-09","winrate_each_day":0.5,"games_played":8,"games_won":4,"aggregate_winrate":0.5024311183144247},{"game_date":"2024-03-10","winrate_each_day":0.6666666666666666,"games_played":3,"games_won":2,"aggregate_winrate":0.5032258064516129},{"game_date":"2024-03-12","winrate_each_day":0.5714285714285714,"games_played":7,"games_won":4,"aggregate_winrate":0.5039872408293461},{"game_date":"2024-03-19","winrate_each_day":0.14285714285714285,"games_played":7,"games_won":1,"aggregate_winrate":0.5},{"game_date":"2024-03-20","winrate_each_day":0.4,"games_played":5,"games_won":2,"aggregate_winrate":0.49921752738654146},{"game_date":"2024-03-21","winrate_each_day":0.6666666666666666,"games_played":3,"games_won":2,"aggregate_winrate":0.5},{"game_date":"2024-03-22","winrate_each_day":0.5,"games_played":6,"games_won":3,"aggregate_winrate":0.5},{"game_date":"2024-04-05","winrate_each_day":0.16666666666666666,"games_played":6,"games_won":1,"aggregate_winrate":0.4969418960244648},{"game_date":"2024-04-06","winrate_each_day":0,"games_played":1,"games_won":0,"aggregate_winrate":0.4961832061068702},{"game_date":"2024-04-07","winrate_each_day":0.2222222222222222,"games_played":9,"games_won":2,"aggregate_winrate":0.4924698795180723},{"game_date":"2024-04-08","winrate_each_day":0.6666666666666666,"games_played":6,"games_won":4,"aggregate_winrate":0.49402985074626865},{"game_date":"2024-04-10","winrate_each_day":0.7777777777777778,"games_played":9,"games_won":7,"aggregate_winrate":0.49779086892488955},{"game_date":"2024-04-11","winrate_each_day":0.25,"games_played":4,"games_won":1,"aggregate_winrate":0.49633967789165445},{"game_date":"2024-04-12","winrate_each_day":0.5,"games_played":12,"games_won":6,"aggregate_winrate":0.49640287769784175},{"game_date":"2024-04-13","winrate_each_day":0.3333333333333333,"games_played":6,"games_won":2,"aggregate_winrate":0.4950071326676177},{"game_date":"2024-04-14","winrate_each_day":0,"games_played":1,"games_won":0,"aggregate_winrate":0.4943019943019943},{"game_date":"2024-04-15","winrate_each_day":0.14285714285714285,"games_played":7,"games_won":1,"aggregate_winrate":0.4908321579689704},{"game_date":"2024-04-17","winrate_each_day":0.2,"games_played":5,"games_won":1,"aggregate_winrate":0.4887955182072829},{"game_date":"2024-04-18","winrate_each_day":0.6,"games_played":10,"games_won":6,"aggregate_winrate":0.4903314917127072},{"game_date":"2024-04-19","winrate_each_day":0.4,"games_played":10,"games_won":4,"aggregate_winrate":0.4891008174386921},{"game_date":"2024-04-20","winrate_each_day":0.8,"games_played":5,"games_won":4,"aggregate_winrate":0.4912043301759134},{"game_date":"2024-04-21","winrate_each_day":0.8888888888888888,"games_played":9,"games_won":8,"aggregate_winrate":0.4959893048128342},{"game_date":"2024-04-22","winrate_each_day":0.2,"games_played":5,"games_won":1,"aggregate_winrate":0.4940239043824701},{"game_date":"2024-04-23","winrate_each_day":1,"games_played":2,"games_won":2,"aggregate_winrate":0.495364238410596},{"game_date":"2024-04-24","winrate_each_day":0,"games_played":2,"games_won":0,"aggregate_winrate":0.4940554821664465},{"game_date":"2024-04-25","winrate_each_day":1,"games_played":1,"games_won":1,"aggregate_winrate":0.4947229551451187},{"game_date":"2024-04-26","winrate_each_day":0.46153846153846156,"games_played":13,"games_won":6,"aggregate_winrate":0.49416342412451364},{"game_date":"2024-04-27","winrate_each_day":0.6666666666666666,"games_played":6,"games_won":4,"aggregate_winrate":0.4954954954954955},{"game_date":"2024-04-28","winrate_each_day":0.3333333333333333,"games_played":3,"games_won":1,"aggregate_winrate":0.4948717948717949},{"game_date":"2024-04-29","winrate_each_day":0.75,"games_played":4,"games_won":3,"aggregate_winrate":0.4961734693877551},{"game_date":"2024-04-30","winrate_each_day":0,"games_played":2,"games_won":0,"aggregate_winrate":0.494910941475827},{"game_date":"2024-05-03","winrate_each_day":0.6666666666666666,"games_played":9,"games_won":6,"aggregate_winrate":0.4968553459119497},{"game_date":"2024-05-06","winrate_each_day":0.5454545454545454,"games_played":11,"games_won":6,"aggregate_winrate":0.4975186104218362},{"game_date":"2024-05-07","winrate_each_day":0.6666666666666666,"games_played":3,"games_won":2,"aggregate_winrate":0.49814585908529047},{"game_date":"2024-05-08","winrate_each_day":1,"games_played":2,"games_won":2,"aggregate_winrate":0.499383477188656},{"game_date":"2024-05-09","winrate_each_day":1,"games_played":4,"games_won":4,"aggregate_winrate":0.501840490797546},{"game_date":"2024-05-10","winrate_each_day":0.4,"games_played":5,"games_won":2,"aggregate_winrate":0.501219512195122},{"game_date":"2024-05-11","winrate_each_day":0.2,"games_played":5,"games_won":1,"aggregate_winrate":0.4993939393939394},{"game_date":"2024-05-12","winrate_each_day":0.5,"games_played":4,"games_won":2,"aggregate_winrate":0.49939686369119424},{"game_date":"2024-05-13","winrate_each_day":0,"games_played":2,"games_won":0,"aggregate_winrate":0.4981949458483754},{"game_date":"2024-05-15","winrate_each_day":0.3333333333333333,"games_played":3,"games_won":1,"aggregate_winrate":0.49760191846522783},{"game_date":"2024-05-16","winrate_each_day":0.5,"games_played":8,"games_won":4,"aggregate_winrate":0.497624703087886},{"game_date":"2024-05-20","winrate_each_day":0.4,"games_played":5,"games_won":2,"aggregate_winrate":0.4970484061393152},{"game_date":"2024-05-21","winrate_each_day":0,"games_played":1,"games_won":0,"aggregate_winrate":0.4964622641509434},{"game_date":"2024-05-22","winrate_each_day":0.6666666666666666,"games_played":6,"games_won":4,"aggregate_winrate":0.49765807962529274},{"game_date":"2024-05-24","winrate_each_day":0.3333333333333333,"games_played":12,"games_won":4,"aggregate_winrate":0.4953810623556582},{"game_date":"2024-05-26","winrate_each_day":0.5,"games_played":6,"games_won":3,"aggregate_winrate":0.4954128440366973},{"game_date":"2024-05-27","winrate_each_day":0.6666666666666666,"games_played":6,"games_won":4,"aggregate_winrate":0.49658314350797267},{"game_date":"2024-05-28","winrate_each_day":0.75,"games_played":4,"games_won":3,"aggregate_winrate":0.4977324263038549},{"game_date":"2024-05-30","winrate_each_day":0.42857142857142855,"games_played":7,"games_won":3,"aggregate_winrate":0.49718785151856015},{"game_date":"2024-06-01","winrate_each_day":0.5,"games_played":4,"games_won":2,"aggregate_winrate":0.49720044792833146},{"game_date":"2024-06-02","winrate_each_day":0.5714285714285714,"games_played":7,"games_won":4,"aggregate_winrate":0.49777777777777776},{"game_date":"2024-06-03","winrate_each_day":0.7142857142857143,"games_played":7,"games_won":5,"aggregate_winrate":0.4994487320837927},{"game_date":"2024-06-05","winrate_each_day":0,"games_played":7,"games_won":0,"aggregate_winrate":0.49562363238512036},{"game_date":"2024-06-06","winrate_each_day":0,"games_played":3,"games_won":0,"aggregate_winrate":0.4940021810250818},{"game_date":"2024-06-07","winrate_each_day":0.3333333333333333,"games_played":9,"games_won":3,"aggregate_winrate":0.4924406047516199},{"game_date":"2024-06-08","winrate_each_day":0.8181818181818182,"games_played":11,"games_won":9,"aggregate_winrate":0.49626467449306294},{"game_date":"2024-06-09","winrate_each_day":0.5454545454545454,"games_played":11,"games_won":6,"aggregate_winrate":0.49683544303797467},{"game_date":"2024-06-10","winrate_each_day":1,"games_played":3,"games_won":3,"aggregate_winrate":0.49842271293375395},{"game_date":"2024-06-11","winrate_each_day":0.8,"games_played":5,"games_won":4,"aggregate_winrate":0.5},{"game_date":"2024-06-12","winrate_each_day":1,"games_played":1,"games_won":1,"aggregate_winrate":0.5005224660397074},{"game_date":"2024-06-13","winrate_each_day":0.625,"games_played":8,"games_won":5,"aggregate_winrate":0.5015544041450777},{"game_date":"2024-06-14","winrate_each_day":0.5,"games_played":2,"games_won":1,"aggregate_winrate":0.5015511892450879},{"game_date":"2024-06-15","winrate_each_day":0,"games_played":1,"games_won":0,"aggregate_winrate":0.5010330578512396},{"game_date":"2024-06-16","winrate_each_day":1,"games_played":2,"games_won":2,"aggregate_winrate":0.5020618556701031},{"game_date":"2024-06-17","winrate_each_day":0.42857142857142855,"games_played":7,"games_won":3,"aggregate_winrate":0.5015353121801432},{"game_date":"2024-06-18","winrate_each_day":0.5,"games_played":4,"games_won":2,"aggregate_winrate":0.5015290519877675},{"game_date":"2024-06-19","winrate_each_day":0.25,"games_played":8,"games_won":2,"aggregate_winrate":0.4994944388270981},{"game_date":"2024-06-21","winrate_each_day":0,"games_played":3,"games_won":0,"aggregate_winrate":0.49798387096774194},{"game_date":"2024-06-24","winrate_each_day":0.7142857142857143,"games_played":7,"games_won":5,"aggregate_winrate":0.4994994994994995},{"game_date":"2024-06-25","winrate_each_day":0,"games_played":3,"games_won":0,"aggregate_winrate":0.49800399201596807},{"game_date":"2024-06-26","winrate_each_day":0.3333333333333333,"games_played":9,"games_won":3,"aggregate_winrate":0.49653808110781406},{"game_date":"2024-06-27","winrate_each_day":1,"games_played":2,"games_won":2,"aggregate_winrate":0.49753208292201384},{"game_date":"2024-06-29","winrate_each_day":0.25,"games_played":4,"games_won":1,"aggregate_winrate":0.49655850540806296},{"game_date":"2024-06-30","winrate_each_day":0.7,"games_played":10,"games_won":7,"aggregate_winrate":0.498539435248296},{"game_date":"2024-07-01","winrate_each_day":0.6666666666666666,"games_played":3,"games_won":2,"aggregate_winrate":0.49902912621359224},{"game_date":"2024-07-03","winrate_each_day":0.5,"games_played":4,"games_won":2,"aggregate_winrate":0.4990328820116054},{"game_date":"2024-07-04","winrate_each_day":1,"games_played":5,"games_won":5,"aggregate_winrate":0.5014436958614052},{"game_date":"2024-07-05","winrate_each_day":0.14285714285714285,"games_played":7,"games_won":1,"aggregate_winrate":0.49904397705544934},{"game_date":"2024-07-06","winrate_each_day":0,"games_played":1,"games_won":0,"aggregate_winrate":0.498567335243553},{"game_date":"2024-07-17","winrate_each_day":0.4,"games_played":5,"games_won":2,"aggregate_winrate":0.49809885931558934},{"game_date":"2024-07-23","winrate_each_day":0,"games_played":1,"games_won":0,"aggregate_winrate":0.4976258309591643},{"game_date":"2024-07-24","winrate_each_day":0.2,"games_played":5,"games_won":1,"aggregate_winrate":0.4962192816635161},{"game_date":"2024-07-25","winrate_each_day":1,"games_played":3,"games_won":3,"aggregate_winrate":0.49764373232799247},{"game_date":"2024-07-26","winrate_each_day":0.6666666666666666,"games_played":3,"games_won":2,"aggregate_winrate":0.4981203007518797},{"game_date":"2024-07-29","winrate_each_day":0.4,"games_played":5,"games_won":2,"aggregate_winrate":0.4976613657623948},{"game_date":"2024-07-30","winrate_each_day":0.5,"games_played":8,"games_won":4,"aggregate_winrate":0.4976787372330548},{"game_date":"2024-07-31","winrate_each_day":0.8571428571428571,"games_played":7,"games_won":6,"aggregate_winrate":0.5},{"game_date":"2024-08-03","winrate_each_day":0,"games_played":6,"games_won":0,"aggregate_winrate":0.4972477064220184},{"game_date":"2024-08-04","winrate_each_day":0.5,"games_played":2,"games_won":1,"aggregate_winrate":0.49725274725274726},{"game_date":"2024-08-05","winrate_each_day":0.5,"games_played":6,"games_won":3,"aggregate_winrate":0.4972677595628415},{"game_date":"2024-08-06","winrate_each_day":0,"games_played":1,"games_won":0,"aggregate_winrate":0.4968152866242038},{"game_date":"2024-08-07","winrate_each_day":0.6923076923076923,"games_played":13,"games_won":9,"aggregate_winrate":0.49910071942446044},{"game_date":"2024-08-08","winrate_each_day":0.8,"games_played":5,"games_won":4,"aggregate_winrate":0.5004476275738585},{"game_date":"2024-08-09","winrate_each_day":0.625,"games_played":8,"games_won":5,"aggregate_winrate":0.5013333333333333},{"game_date":"2024-08-10","winrate_each_day":0.3333333333333333,"games_played":6,"games_won":2,"aggregate_winrate":0.5004420866489832},{"game_date":"2024-08-12","winrate_each_day":0.6666666666666666,"games_played":3,"games_won":2,"aggregate_winrate":0.5008818342151675},{"game_date":"2024-08-13","winrate_each_day":0.5555555555555556,"games_played":9,"games_won":5,"aggregate_winrate":0.5013123359580053},{"game_date":"2024-08-14","winrate_each_day":0.4,"games_played":10,"games_won":4,"aggregate_winrate":0.5004336513443192},{"game_date":"2024-08-15","winrate_each_day":0.7142857142857143,"games_played":7,"games_won":5,"aggregate_winrate":0.5017241379310344},{"game_date":"2024-08-16","winrate_each_day":0.5454545454545454,"games_played":11,"games_won":6,"aggregate_winrate":0.502134927412468},{"game_date":"2024-08-17","winrate_each_day":0.5555555555555556,"games_played":9,"games_won":5,"aggregate_winrate":0.502542372881356},{"game_date":"2024-08-18","winrate_each_day":0,"games_played":5,"games_won":0,"aggregate_winrate":0.5004219409282701},{"game_date":"2024-08-19","winrate_each_day":0.5,"games_played":2,"games_won":1,"aggregate_winrate":0.5004212299915753},{"game_date":"2024-08-20","winrate_each_day":0.3333333333333333,"games_played":9,"games_won":3,"aggregate_winrate":0.4991638795986622},{"game_date":"2024-08-21","winrate_each_day":0.625,"games_played":8,"games_won":5,"aggregate_winrate":0.5},{"game_date":"2024-08-23","winrate_each_day":0.5714285714285714,"games_played":7,"games_won":4,"aggregate_winrate":0.500412881915772},{"game_date":"2024-08-24","winrate_each_day":0,"games_played":2,"games_won":0,"aggregate_winrate":0.49958779884583676},{"game_date":"2024-08-26","winrate_each_day":0.6,"games_played":5,"games_won":3,"aggregate_winrate":0.5},{"game_date":"2024-08-27","winrate_each_day":0.6,"games_played":5,"games_won":3,"aggregate_winrate":0.5004088307440719},{"game_date":"2024-08-28","winrate_each_day":0,"games_played":1,"games_won":0,"aggregate_winrate":0.5},{"game_date":"2024-08-29","winrate_each_day":0.2222222222222222,"games_played":9,"games_won":2,"aggregate_winrate":0.49797242497972427},{"game_date":"2024-08-30","winrate_each_day":0.6666666666666666,"games_played":3,"games_won":2,"aggregate_winrate":0.49838187702265374},{"game_date":"2024-09-01","winrate_each_day":0.6666666666666666,"games_played":6,"games_won":4,"aggregate_winrate":0.499194847020934},{"game_date":"2024-09-02","winrate_each_day":0.6666666666666666,"games_played":6,"games_won":4,"aggregate_winrate":0.5},{"game_date":"2024-09-03","winrate_each_day":0.6,"games_played":10,"games_won":6,"aggregate_winrate":0.5007949125596184},{"game_date":"2024-09-04","winrate_each_day":0.375,"games_played":8,"games_won":3,"aggregate_winrate":0.5},{"game_date":"2024-09-06","winrate_each_day":0,"games_played":5,"games_won":0,"aggregate_winrate":0.4980330448465775},{"game_date":"2024-09-07","winrate_each_day":0,"games_played":4,"games_won":0,"aggregate_winrate":0.4964705882352941},{"game_date":"2024-09-09","winrate_each_day":0.5,"games_played":10,"games_won":5,"aggregate_winrate":0.4964980544747082},{"game_date":"2024-09-10","winrate_each_day":0,"games_played":3,"games_won":0,"aggregate_winrate":0.4953416149068323},{"game_date":"2024-09-11","winrate_each_day":0.2,"games_played":5,"games_won":1,"aggregate_winrate":0.494199535962877},{"game_date":"2024-09-13","winrate_each_day":1,"games_played":1,"games_won":1,"aggregate_winrate":0.4945904173106646},{"game_date":"2024-09-14","winrate_each_day":0,"games_played":3,"games_won":0,"aggregate_winrate":0.49344641480339246},{"game_date":"2024-09-17","winrate_each_day":0.6,"games_played":10,"games_won":6,"aggregate_winrate":0.49426166794185156},{"game_date":"2024-09-18","winrate_each_day":0.6666666666666666,"games_played":6,"games_won":4,"aggregate_winrate":0.49504950495049505},{"game_date":"2024-09-19","winrate_each_day":0.42857142857142855,"games_played":7,"games_won":3,"aggregate_winrate":0.4946969696969697},{"game_date":"2024-09-20","winrate_each_day":0.5,"games_played":2,"games_won":1,"aggregate_winrate":0.4947049924357035},{"game_date":"2024-09-22","winrate_each_day":0.16666666666666666,"games_played":6,"games_won":1,"aggregate_winrate":0.4932228915662651},{"game_date":"2024-09-23","winrate_each_day":0.6666666666666666,"games_played":9,"games_won":6,"aggregate_winrate":0.4943904263275991},{"game_date":"2024-09-25","winrate_each_day":0.42857142857142855,"games_played":7,"games_won":3,"aggregate_winrate":0.49404761904761907},{"game_date":"2024-09-27","winrate_each_day":1,"games_played":5,"games_won":5,"aggregate_winrate":0.49592290585618976},{"game_date":"2024-09-28","winrate_each_day":0.6666666666666666,"games_played":3,"games_won":2,"aggregate_winrate":0.496301775147929},{"game_date":"2024-09-30","winrate_each_day":0.8333333333333334,"games_played":6,"games_won":5,"aggregate_winrate":0.49779086892488955},{"game_date":"2024-10-01","winrate_each_day":0.5,"games_played":4,"games_won":2,"aggregate_winrate":0.4977973568281938},{"game_date":"2024-10-02","winrate_each_day":0.6666666666666666,"games_played":6,"games_won":4,"aggregate_winrate":0.49853801169590645},{"game_date":"2024-10-04","winrate_each_day":0.75,"games_played":4,"games_won":3,"aggregate_winrate":0.49927113702623904},{"game_date":"2024-10-06","winrate_each_day":0.3333333333333333,"games_played":3,"games_won":1,"aggregate_winrate":0.4989090909090909},{"game_date":"2024-10-08","winrate_each_day":0.3333333333333333,"games_played":6,"games_won":2,"aggregate_winrate":0.498189717595945},{"game_date":"2024-10-09","winrate_each_day":0.5,"games_played":6,"games_won":3,"aggregate_winrate":0.498197548666186},{"game_date":"2024-10-10","winrate_each_day":0,"games_played":1,"games_won":0,"aggregate_winrate":0.4978386167146974},{"game_date":"2024-10-14","winrate_each_day":0,"games_played":4,"games_won":0,"aggregate_winrate":0.4964080459770115},{"game_date":"2024-10-15","winrate_each_day":0.5,"games_played":8,"games_won":4,"aggregate_winrate":0.49642857142857144},{"game_date":"2024-10-18","winrate_each_day":0.5,"games_played":6,"games_won":3,"aggregate_winrate":0.49644381223328593},{"game_date":"2024-10-23","winrate_each_day":0.6,"games_played":5,"games_won":3,"aggregate_winrate":0.4968107725017718},{"game_date":"2024-10-24","winrate_each_day":0.2,"games_played":5,"games_won":1,"aggregate_winrate":0.4957627118644068},{"game_date":"2024-10-25","winrate_each_day":0.2,"games_played":5,"games_won":1,"aggregate_winrate":0.49472202674173116},{"game_date":"2024-10-26","winrate_each_day":0.5,"games_played":6,"games_won":3,"aggregate_winrate":0.49474421864050455},{"game_date":"2024-10-27","winrate_each_day":0.625,"games_played":8,"games_won":5,"aggregate_winrate":0.49547038327526133},{"game_date":"2024-10-28","winrate_each_day":0,"games_played":1,"games_won":0,"aggregate_winrate":0.49512534818941506},{"game_date":"2024-10-29","winrate_each_day":0.5,"games_played":2,"games_won":1,"aggregate_winrate":0.4951321279554937},{"game_date":"2024-10-31","winrate_each_day":0.5,"games_played":6,"games_won":3,"aggregate_winrate":0.4951523545706371},{"game_date":"2024-11-01","winrate_each_day":0.6363636363636364,"games_played":11,"games_won":7,"aggregate_winrate":0.4962199312714777},{"game_date":"2024-11-02","winrate_each_day":1,"games_played":1,"games_won":1,"aggregate_winrate":0.4965659340659341},{"game_date":"2024-11-04","winrate_each_day":0.3333333333333333,"games_played":9,"games_won":3,"aggregate_winrate":0.4955631399317406},{"game_date":"2024-11-05","winrate_each_day":0.4,"games_played":10,"games_won":4,"aggregate_winrate":0.49491525423728816},{"game_date":"2024-11-06","winrate_each_day":0.6666666666666666,"games_played":9,"games_won":6,"aggregate_winrate":0.49595687331536387},{"game_date":"2024-11-07","winrate_each_day":0.25,"games_played":4,"games_won":1,"aggregate_winrate":0.4952956989247312},{"game_date":"2024-11-08","winrate_each_day":0,"games_played":2,"games_won":0,"aggregate_winrate":0.49463087248322146},{"game_date":"2024-11-10","winrate_each_day":0.5,"games_played":2,"games_won":1,"aggregate_winrate":0.49463806970509383},{"game_date":"2024-11-11","winrate_each_day":0.75,"games_played":4,"games_won":3,"aggregate_winrate":0.49532085561497324},{"game_date":"2024-11-12","winrate_each_day":0.25,"games_played":8,"games_won":2,"aggregate_winrate":0.4940159574468085},{"game_date":"2024-11-13","winrate_each_day":0.6666666666666666,"games_played":12,"games_won":8,"aggregate_winrate":0.4953825857519789},{"game_date":"2024-11-14","winrate_each_day":0.5714285714285714,"games_played":7,"games_won":4,"aggregate_winrate":0.49573210768220616},{"game_date":"2024-11-15","winrate_each_day":0.5,"games_played":4,"games_won":2,"aggregate_winrate":0.495743287491814},{"game_date":"2024-11-20","winrate_each_day":0.3333333333333333,"games_played":3,"games_won":1,"aggregate_winrate":0.4954248366013072},{"game_date":"2024-11-24","winrate_each_day":0.3333333333333333,"games_played":3,"games_won":1,"aggregate_winrate":0.49510763209393344},{"game_date":"2024-11-25","winrate_each_day":0.8571428571428571,"games_played":7,"games_won":6,"aggregate_winrate":0.4967532467532468},{"game_date":"2024-11-27","winrate_each_day":0.5,"games_played":6,"games_won":3,"aggregate_winrate":0.49676584734799484},{"game_date":"2024-11-28","winrate_each_day":0.75,"games_played":8,"games_won":6,"aggregate_winrate":0.4980694980694981},{"game_date":"2024-11-29","winrate_each_day":0.5454545454545454,"games_played":11,"games_won":6,"aggregate_winrate":0.4984025559105431},{"game_date":"2024-12-02","winrate_each_day":0.3333333333333333,"games_played":3,"games_won":1,"aggregate_winrate":0.49808673469387754},{"game_date":"2024-12-03","winrate_each_day":0.25,"games_played":4,"games_won":1,"aggregate_winrate":0.49745547073791346},{"game_date":"2024-12-04","winrate_each_day":0.3333333333333333,"games_played":9,"games_won":3,"aggregate_winrate":0.4965211891208096},{"game_date":"2024-12-05","winrate_each_day":0.5,"games_played":8,"games_won":4,"aggregate_winrate":0.49653870358716173},{"game_date":"2024-12-06","winrate_each_day":0,"games_played":3,"games_won":0,"aggregate_winrate":0.4956030150753769},{"game_date":"2024-12-07","winrate_each_day":0.5714285714285714,"games_played":7,"games_won":4,"aggregate_winrate":0.4959349593495935},{"game_date":"2024-12-08","winrate_each_day":0,"games_played":3,"games_won":0,"aggregate_winrate":0.4950062421972534},{"game_date":"2024-12-09","winrate_each_day":0.375,"games_played":8,"games_won":3,"aggregate_winrate":0.49440993788819876},{"game_date":"2024-12-10","winrate_each_day":0.7058823529411765,"games_played":17,"games_won":12,"aggregate_winrate":0.49661954517516904},{"game_date":"2024-12-11","winrate_each_day":0.3333333333333333,"games_played":6,"games_won":2,"aggregate_winrate":0.4960195958358849},{"game_date":"2024-12-13","winrate_each_day":1,"games_played":1,"games_won":1,"aggregate_winrate":0.496328029375765},{"game_date":"2024-12-18","winrate_each_day":1,"games_played":5,"games_won":5,"aggregate_winrate":0.4978645515558267},{"game_date":"2024-12-19","winrate_each_day":0.16666666666666666,"games_played":6,"games_won":1,"aggregate_winrate":0.4966565349544073},{"game_date":"2024-12-20","winrate_each_day":0.6153846153846154,"games_played":13,"games_won":8,"aggregate_winrate":0.49758745476477684},{"game_date":"2024-12-21","winrate_each_day":1,"games_played":2,"games_won":2,"aggregate_winrate":0.49819277108433735},{"game_date":"2024-12-25","winrate_each_day":0.2,"games_played":5,"games_won":1,"aggregate_winrate":0.4972972972972973},{"game_date":"2024-12-26","winrate_each_day":0.4,"games_played":5,"games_won":2,"aggregate_winrate":0.49700598802395207},{"game_date":"2024-12-30","winrate_each_day":1,"games_played":1,"games_won":1,"aggregate_winrate":0.49730700179533216},{"game_date":"2024-12-31","winrate_each_day":0,"games_played":1,"games_won":0,"aggregate_winrate":0.49700956937799046},{"game_date":"2025-01-01","winrate_each_day":0.2857142857142857,"games_played":7,"games_won":2,"aggregate_winrate":0.49612864800476475},{"game_date":"2025-01-06","winrate_each_day":0.6666666666666666,"games_played":6,"games_won":4,"aggregate_winrate":0.4967359050445104},{"game_date":"2025-01-08","winrate_each_day":0.8181818181818182,"games_played":11,"games_won":9,"aggregate_winrate":0.4988207547169811},{"game_date":"2025-01-09","winrate_each_day":0.5555555555555556,"games_played":9,"games_won":5,"aggregate_winrate":0.4991202346041056},{"game_date":"2025-01-10","winrate_each_day":0.8571428571428571,"games_played":7,"games_won":6,"aggregate_winrate":0.5005841121495327},{"game_date":"2025-01-11","winrate_each_day":0.8,"games_played":5,"games_won":4,"aggregate_winrate":0.5014560279557367},{"game_date":"2025-01-12","winrate_each_day":0.5,"games_played":4,"games_won":2,"aggregate_winrate":0.5014526438117374},{"game_date":"2025-01-13","winrate_each_day":1,"games_played":5,"games_won":5,"aggregate_winrate":0.5028968713789108},{"game_date":"2025-01-14","winrate_each_day":0.1111111111111111,"games_played":9,"games_won":1,"aggregate_winrate":0.500864553314121},{"game_date":"2025-01-15","winrate_each_day":0,"games_played":2,"games_won":0,"aggregate_winrate":0.5002878526194589}]